ram.v
module ram(
        input   wire            clk,
        input   wire            reset_n,
        input   wire            we,
        input   wire    [31:0]  addr,
        output  wire    [31:0]  data_read,
        input   wire    [31:0]  data_write
    );

    reg [31:0] ram_block[255:0];

    /*  read  */
    assign data_read = ram_block[addr];

    integer i;
    always @(posedge clk or negedge reset_n)
    begin
        if(!reset_n)
        begin
            /*  reset  */
            for(i=0;i<255;i=i+1)
                ram_block[i] = 32'h0;
        end
        else
        begin
            /*  write  */
            if(we)
                ram_block[addr] <= data_write;
        end
    end

endmodule // ram

Src/alu.v
module alu(
        input   wire    [31:0]  A,
        input   wire    [31:0]  B,
        input   wire    [2:0]   F,
        output  reg     [31:0]  Y,
        output  wire    	    zero
    );

    /*  Y  */
    always@(*)
    begin 
        case(F)
            3'b000:     Y = A & B;
            3'b001:     Y = A | B;
            3'b010:     Y = A + B;

            3'b100:     Y = A & (~B);
            3'b101:     Y = A | (~B);

            3'b110:     Y = A - B;
            3'b111:     Y = (A < B) ? 1 : 0;

            default:    Y = 32'hxxxxxxxx;
        endcase
    end

    /*  zero  */
    assign zero = (A == B) ? 1 : 0;

endmodule // alu

register.v
module register(
        input   wire            clk,
        input   wire            reset_n,

        input   wire    [4:0]   addr1,
        output  wire    [31:0]  read1,

        input   wire    [4:0]   addr2,
        output  wire    [31:0]  read2,

        input   wire            we3,
        input   wire    [4:0]   addr3,
        input   wire    [31:0]  write3
    );

    reg [31:0] register_block [31:0];

    assign read1 = register_block[addr1];
    assign read2 = register_block[addr2];

    integer i;
    always @(posedge clk or negedge reset_n)
    begin
        if(!reset_n)
        begin
            /*  reset  */
            for(i=0;i<32;i=i+1)
                register_block[i] = 32'h0;
        end
        else
        begin
            /*  write  */
            if(we3)
            register_block[addr3] <= write3;
        end
    end

endmodule // register

cu.v
module cu(
        input   wire            reset_n,

        input   wire    [5:0]   op,
        input   wire    [5:0]   funct,

        output  reg             reg_write,
        output  reg             reg_dst,
        output  reg             alu_src,
        output  reg             branch,
        output  reg             mem_write,
        output  reg             mem_to_reg,
        output  reg     [2:0]   alu_control
    );

    reg [1:0] alu_op;

    always @(*)
    begin
		if(!reset_n)
		begin
            reg_write       = 0;
            reg_dst         = 0;
            alu_src         = 0;
            branch          = 0;
            mem_write       = 0;
            mem_to_reg      = 0;
            alu_op          = 2'h0;
        end
        else
        begin
            /*  main decoder  */
            // TODO
            case(op)
                /*  R-type instructions  */
                6'b000000:
                begin
                    reg_write = 1;
                    reg_dst = 1;
                    alu_src = 0;
                    branch = 0;
                    mem_write = 0;
                    mem_to_reg = 0;
                    alu_op = 2'b10;
                end

                /*  Memory instructions - lw  */ 
                6'b100011:
                begin
                    reg_write = 1;
                    reg_dst = 0;
                    alu_src = 1;
                    branch = 0;
                    mem_write = 0;
                    mem_to_reg = 1;
                    alu_op = 2'b00;
                end

                /*  Memory instructions - sw  */ 
                6'b101011:
                begin
                    reg_write = 0;
                    reg_dst = 0;    // X
                    alu_src = 1;
                    branch = 0;
                    mem_write = 1;
                    mem_to_reg = 0; // X
                    alu_op = 2'b00;
                end

                /*  Branch instructions - beq  */ 
                6'b000100:
                begin
                    reg_write = 0;
                    reg_dst = 0;    // X
                    alu_src = 0;
                    branch = 1;
                    mem_write = 0;
                    mem_to_reg = 0; // X
                    alu_op = 2'b01;
                end

                default:
                begin
                    reg_write = 1'hx;
                    reg_dst = 1'hx;
                    alu_src = 1'hx;
                    branch = 1'hx;
                    mem_write = 1'hx;
                    mem_to_reg = 1'hx;
                    alu_op = 2'bxx;
                end	 
            endcase
        end
    end

    /*  ALU Decoder  */
    always@(*)
    begin
        case (alu_op)
            2'b00: 
            begin
                alu_control = 3'b010;   // add
            end

            2'b01: 
            begin
                alu_control = 3'b110;   // sub
            end

            2'b10: 
            begin
                case(funct)
                    6'b100000:  alu_control = 3'b010;   // add
                    6'b100010:  alu_control = 3'b110;   // sub
                    6'b100100:  alu_control = 3'b000;   // and
                    6'b100101:  alu_control = 3'b001;   // or
                    6'b101010:  alu_control = 3'b111;   // slt
                    default:    alu_control = 3'bxxx;
                endcase
            end

            default: 
            begin
                alu_control = 3'bxxx;
            end
        endcase
    end
endmodule // cu

rom.v
module rom(
        output  wire    [31:0]  dout,
        input   wire    [10:0]  addr
    );

    reg [7:0] rom_block [1023:0];

    assign dout = {rom_block[addr], rom_block[addr+1], rom_block[addr+2], rom_block[addr+3]};

endmodule // rom

top.v
//`define __QUARTUS__
`ifndef __QUARTUS__
    `include "alu.v"
    `include "cu.v"
    `include "ram.v"
    `include "register.v"
    `include "rom.v"
`endif

module top(
	input   wire    clk,
	input   wire    reset_n
);

    // ROM
    wire    [31:0]  rom_dout        ;
    wire    [10:0]  rom_addr        ;

    // CU
    wire    [5:0]   cu_op           ;
    wire    [5:0]   cu_funct        ;
    wire            cu_reg_write    ;
    wire            cu_reg_dst      ;
    wire            cu_alu_src      ;
    wire            cu_branch       ;
    wire            cu_mem_write    ;
    wire            cu_mem_to_reg   ;
    wire    [2:0]   cu_alu_control  ;

    // ALU
    wire    [31:0]  alu_A           ;
    wire    [31:0]  alu_B           ;
    wire    [2:0]   alu_F           ;
    wire    [31:0]  alu_result      ;
    wire            alu_zero        ;

    // register
    wire    [4:0]   reg_addr1       ;
    wire    [31:0]  reg_read1       ;

    wire    [4:0]   reg_addr2       ;
    wire    [31:0]  reg_read2       ;

    wire            reg_we3         ;
    wire    [4:0]   reg_addr3       ;
    wire    [31:0]  reg_write3      ;

    // RAM
    wire            ram_we          ;
    wire    [31:0]  ram_addr        ;
    wire    [31:0]  ram_read        ;
    wire    [31:0]  ram_write       ;


    rom  u_rom (
        .dout           (   rom_dout        ),
        .addr           (   rom_addr        )
    );

    cu  u_cu (
        .reset_n        (   reset_n         ),
        
        .op             (   cu_op           ),
        .funct          (   cu_funct        ),

        .reg_write      (   cu_reg_write    ),
        .reg_dst        (   cu_reg_dst      ),
        .alu_src        (   cu_alu_src      ),
        .branch         (   cu_branch       ),
        .mem_write      (   cu_mem_write    ),
        .mem_to_reg     (   cu_mem_to_reg   ),
        .alu_control    (   cu_alu_control  )
    );

    register  u_register (
        .clk            (   clk             ),
        .reset_n        (   reset_n         ),
        .addr1          (   reg_addr1       ),
        .read1          (   reg_read1       ),
        .addr2          (   reg_addr2       ),
        .read2          (   reg_read2       ),
        .we3            (   reg_we3         ),
        .addr3          (   reg_addr3       ),
        .write3         (   reg_write3      )
    );

    alu  u_alu (
        .A              (   alu_A           ),
        .B              (   alu_B           ),
        .F              (   alu_F           ),
        .Y              (   alu_result      ),
        .zero           (   alu_zero        )
    );

    ram  u_ram (
        .clk            (   clk             ),
        .reset_n        (   reset_n         ),
        .we             (   ram_we          ),
        .addr           (   ram_addr        ),
        .data_read      (   ram_read        ),
        .data_write     (   ram_write       )
    );

    wire [10:0] pc;
    reg [10:0] pc_d = 11'h0;
    wire pc_src;
    wire [10:0] pc_branch;
    wire [10:0] pc_plus4;

    // pc
    assign pc_src = cu_branch & alu_zero;
    assign pc = pc_src ? pc_branch : pc_plus4;
    assign pc_plus4 = pc_d + 4;

    // pc_ff
    always @(posedge clk or negedge reset_n)
	begin
        if(!reset_n)
			pc_d <= 11'h0;
        else
			pc_d <= pc;
    end

    assign rom_addr = pc_d;

    wire [31:0] instr = rom_dout;

    // rom to cu
    assign cu_op    = instr[31:26];
    assign cu_funct = instr[5:0];

    // rom to reg
    wire result;

    assign reg_addr1    = instr[25:21];
    assign reg_addr2    = instr[20:16];
    assign reg_addr3    = cu_reg_dst ? instr[15:11] : instr[20:16];
    assign reg_we3      = cu_reg_write;
    assign reg_write3   = result;

    // sign extend
    wire [31:0] signImm = {{16{instr[15]}},instr[15:0]};
    assign pc_branch = pc_plus4 + (signImm << 2);

    // reg to alu
    assign alu_A = reg_read1;
    assign alu_B = cu_alu_src ? signImm : reg_read2;
    assign alu_F = cu_alu_control;

    // alu to ram
    assign ram_addr = alu_result;
    assign ram_write = reg_read2;
    assign ram_we = cu_mem_write;

    assign result = cu_mem_to_reg ? ram_read : alu_result;


endmodule // top

top_tb.v
`timescale 1ns/100ps

//`define __QUARTUS__
`ifndef __QUARTUS__
    `include "top.v"
`endif

module top_tb;

    reg clk = 0;
    reg reset_n = 1;

    /*  Instance  */
    top u_top(clk,reset_n);

    always
        #10 clk=~clk;

    integer i;
    initial
    begin
        $dumpfile("top.vcd");
        $dumpvars(0,top_tb);

        // load file
        $readmemb("rom.dat",u_top.u_rom.rom_block);

        #20 reset_n = 0;
        #20 reset_n = 1;

        #200 $finish;
    end
endmodule

top.vcd
$date
	Sat Nov 16 16:55:30 2019
$end
$version
	Icarus Verilog
$end
$timescale
	100ps
$end
$scope module top_tb $end
$var reg 1 ! clk $end
$var reg 1 " reset_n $end
$scope module u_top $end
$var wire 32 # alu_A [31:0] $end
$var wire 3 $ alu_F [2:0] $end
$var wire 1 ! clk $end
$var wire 32 % instr [31:0] $end
$var wire 1 & pc_src $end
$var wire 32 ' ram_addr [31:0] $end
$var wire 1 ( ram_we $end
$var wire 32 ) ram_write [31:0] $end
$var wire 1 * reg_we3 $end
$var wire 1 " reset_n $end
$var wire 11 + rom_addr [10:0] $end
$var wire 32 , signImm [31:0] $end
$var wire 32 - rom_dout [31:0] $end
$var wire 1 . result $end
$var wire 32 / reg_write3 [31:0] $end
$var wire 32 0 reg_read2 [31:0] $end
$var wire 32 1 reg_read1 [31:0] $end
$var wire 5 2 reg_addr3 [4:0] $end
$var wire 5 3 reg_addr2 [4:0] $end
$var wire 5 4 reg_addr1 [4:0] $end
$var wire 32 5 ram_read [31:0] $end
$var wire 11 6 pc_plus4 [10:0] $end
$var wire 11 7 pc_branch [10:0] $end
$var wire 11 8 pc [10:0] $end
$var wire 1 9 cu_reg_write $end
$var wire 1 : cu_reg_dst $end
$var wire 6 ; cu_op [5:0] $end
$var wire 1 < cu_mem_write $end
$var wire 1 = cu_mem_to_reg $end
$var wire 6 > cu_funct [5:0] $end
$var wire 1 ? cu_branch $end
$var wire 1 @ cu_alu_src $end
$var wire 3 A cu_alu_control [2:0] $end
$var wire 1 B alu_zero $end
$var wire 32 C alu_result [31:0] $end
$var wire 32 D alu_B [31:0] $end
$var reg 11 E pc_d [10:0] $end
$scope module u_alu $end
$var wire 32 F A [31:0] $end
$var wire 32 G B [31:0] $end
$var wire 3 H F [2:0] $end
$var wire 1 B zero $end
$var reg 32 I Y [31:0] $end
$upscope $end
$scope module u_cu $end
$var wire 6 J funct [5:0] $end
$var wire 6 K op [5:0] $end
$var wire 1 " reset_n $end
$var reg 3 L alu_control [2:0] $end
$var reg 2 M alu_op [1:0] $end
$var reg 1 @ alu_src $end
$var reg 1 ? branch $end
$var reg 1 = mem_to_reg $end
$var reg 1 < mem_write $end
$var reg 1 : reg_dst $end
$var reg 1 9 reg_write $end
$upscope $end
$scope module u_ram $end
$var wire 32 N addr [31:0] $end
$var wire 1 ! clk $end
$var wire 32 O data_read [31:0] $end
$var wire 32 P data_write [31:0] $end
$var wire 1 " reset_n $end
$var wire 1 ( we $end
$var integer 32 Q i [31:0] $end
$upscope $end
$scope module u_register $end
$var wire 5 R addr1 [4:0] $end
$var wire 5 S addr2 [4:0] $end
$var wire 5 T addr3 [4:0] $end
$var wire 1 ! clk $end
$var wire 32 U read1 [31:0] $end
$var wire 32 V read2 [31:0] $end
$var wire 1 " reset_n $end
$var wire 1 * we3 $end
$var wire 32 W write3 [31:0] $end
$var integer 32 X i [31:0] $end
$upscope $end
$scope module u_rom $end
$var wire 11 Y addr [10:0] $end
$var wire 32 Z dout [31:0] $end
$upscope $end
$upscope $end
$upscope $end
$enddefinitions $end
#0
$dumpvars
b1000100001100000100010 Z
b0 Y
bx X
b0x W
bx V
bx U
b11 T
b10 S
b1 R
bx Q
bx P
bx O
bx N
b10 M
b110 L
b0 K
b100010 J
bx I
b110 H
bx G
bx F
b0 E
bx D
bx C
xB
b110 A
0@
0?
b100010 >
0=
0<
b0 ;
1:
19
b100 8
b10001100 7
b100 6
bx 5
b1 4
b10 3
b11 2
bx 1
bx 0
b0x /
x.
b1000100001100000100010 -
b1100000100010 ,
b0 +
1*
bx )
0(
bx '
0&
b1000100001100000100010 %
b110 $
bx #
1"
0!
$end
#100
b0 D
b0 G
b0 M
1=
1@
0:
b100 2
b100 T
b10 $
b10 H
b10 A
b10 L
b1000 7
b1000 8
b100011 ;
b100011 K
b100 3
b100 S
b0 >
b0 J
b0 ,
b1000 6
b10001100001001000000000000000000 %
b10001100001001000000000000000000 -
b10001100001001000000000000000000 Z
b100 +
b100 Y
b100 E
1!
#200
b10 2
b10 T
b10001100 7
b100 8
b0 ;
b0 K
b10 3
b10 S
b100010 >
b100010 J
b1100000100010 ,
b100 6
b1000100001100000100010 %
b1000100001100000100010 -
b1000100001100000100010 Z
b0 +
b0 Y
b0 E
b0 /
b0 W
0.
1B
b0 5
b0 O
b0 '
b0 N
b0 C
b0 I
0=
0@
0*
09
b11111111 Q
b0 )
b0 P
b0 0
b0 V
b0 #
b0 F
b0 1
b0 U
b100000 X
0!
0"
#300
b100000 X
b11111111 Q
1!
#400
b110 $
b110 H
b110 A
b110 L
b11 2
b11 T
b10 M
1:
1*
19
0!
1"
#500
b0 /
b0 W
0.
b0 5
b0 O
b0 '
b0 N
b0 C
b0 I
b0 M
1=
1@
0:
b100 2
b100 T
b10 $
b10 H
b10 A
b10 L
b1000 7
b1000 8
b100011 ;
b100011 K
b100 3
b100 S
b0 >
b0 J
b0 ,
b1000 6
b10001100001001000000000000000000 %
b10001100001001000000000000000000 -
b10001100001001000000000000000000 Z
b100 +
b100 Y
b100 E
1!
#600
0!
#700
0=
1(
1<
0*
09
b1100 7
b1100 8
b101011 ;
b101011 K
b1100 6
b10101100001001000000000000000000 %
b10101100001001000000000000000000 -
b10101100001001000000000000000000 Z
b1000 +
b1000 Y
b1000 E
1!
#800
0!
#900
b110 $
b110 H
b110 A
b110 L
1&
b1 M
0(
0<
1?
0@
b0 2
b0 T
b10000 7
b10000 8
b100 ;
b100 K
b0 4
b0 R
b0 3
b0 S
b10000 6
b10000000000000000000000000000 %
b10000000000000000000000000000 -
b10000000000000000000000000000 Z
b1100 +
b1100 Y
b1100 E
1!
#1000
0!
#1100
b0x /
b0x W
x.
bx $
bx H
bx A
bx L
x&
xB
bx 8
bx M
x=
x(
x<
x?
x@
x:
x*
x9
bx 5
bx O
bx '
bx N
bx C
bx I
bx D
bx G
bx 2
bx T
bx 7
bx ;
bx K
bx #
bx F
bx 1
bx U
bx 4
bx R
bx )
bx P
bx 0
bx V
bx 3
bx S
bx >
bx J
bx ,
b10100 6
bx %
bx -
bx Z
b10000 +
b10000 Y
b10000 E
1!
#1200
0!
#1300
bx 6
bx +
bx Y
bx E
1!
